<annotation>
	<folder>paper</folder>
	<filename>74663a5385.jpg</filename>
	<path>D:\chosen_waste_photos\paper\74663a5385.jpg</path>
	<source>
		<database>Unknown</database>
	</source>
	<size>
		<width>265</width>
		<height>190</height>
		<depth>3</depth>
	</size>
	<segmented>0</segmented>
	<object>
		<name>paper</name>
		<pose>Unspecified</pose>
		<truncated>1</truncated>
		<difficult>0</difficult>
		<bndbox>
			<xmin>197</xmin>
			<ymin>134</ymin>
			<xmax>265</xmax>
			<ymax>176</ymax>
		</bndbox>
	</object>
	<object>
		<name>paper</name>
		<pose>Unspecified</pose>
		<truncated>1</truncated>
		<difficult>0</difficult>
		<bndbox>
			<xmin>107</xmin>
			<ymin>1</ymin>
			<xmax>170</xmax>
			<ymax>89</ymax>
		</bndbox>
	</object>
	<object>
		<name>paper</name>
		<pose>Unspecified</pose>
		<truncated>0</truncated>
		<difficult>0</difficult>
		<bndbox>
			<xmin>145</xmin>
			<ymin>4</ymin>
			<xmax>216</xmax>
			<ymax>105</ymax>
		</bndbox>
	</object>
	<object>
		<name>paper</name>
		<pose>Unspecified</pose>
		<truncated>0</truncated>
		<difficult>0</difficult>
		<bndbox>
			<xmin>130</xmin>
			<ymin>67</ymin>
			<xmax>215</xmax>
			<ymax>178</ymax>
		</bndbox>
	</object>
	<object>
		<name>paper</name>
		<pose>Unspecified</pose>
		<truncated>0</truncated>
		<difficult>0</difficult>
		<bndbox>
			<xmin>202</xmin>
			<ymin>52</ymin>
			<xmax>259</xmax>
			<ymax>109</ymax>
		</bndbox>
	</object>
	<object>
		<name>paper</name>
		<pose>Unspecified</pose>
		<truncated>0</truncated>
		<difficult>0</difficult>
		<bndbox>
			<xmin>3</xmin>
			<ymin>77</ymin>
			<xmax>145</xmax>
			<ymax>175</ymax>
		</bndbox>
	</object>
	<object>
		<name>paper</name>
		<pose>Unspecified</pose>
		<truncated>1</truncated>
		<difficult>0</difficult>
		<bndbox>
			<xmin>1</xmin>
			<ymin>35</ymin>
			<xmax>58</xmax>
			<ymax>82</ymax>
		</bndbox>
	</object>
</annotation>
